playlist_mixer/cli.py
playlist_mixer/config.py
playlist_mixer/spotify.py
playlist_mixer-0.11.0.dist-info/METADATA
playlist_mixer-0.11.0.dist-info/WHEEL
playlist_mixer-0.11.0.dist-info/entry_points.txt
playlist_mixer-0.11.0.dist-info/RECORD
