Metadata-Version: 2.3
Name: playlist-mixer
Version: 0.11.0
Summary: Playlist Mixer for Spotify
Author: Jan Dittrich
Author-email: mail@jand.one
Requires-Python: >=3.13,<4.0
Classifier: Programming Language :: Python :: 3
Classifier: Programming Language :: Python :: 3.13
Requires-Dist: click (>=8.1.7,<9.0.0)
Requires-Dist: spotipy (>=2.24.0,<3.0.0)
